filter_functions/__init__.py
filter_functions/analytic.py
filter_functions/basis.py
filter_functions/gradient.py
filter_functions/numeric.py
filter_functions/plotting.py
filter_functions/pulse_sequence.py
filter_functions/superoperator.py
filter_functions/types.py
filter_functions/util.py
filter_functions-1.2.0.dist-info/METADATA
filter_functions-1.2.0.dist-info/WHEEL
filter_functions-1.2.0.dist-info/licenses/LICENSE
filter_functions-1.2.0.dist-info/RECORD
