Metadata-Version: 2.4
Name: filter_functions
Version: 1.2.0
Summary: Package for efficient calculation of generalized filter functions
Project-URL: Source, https://github.com/qutech/filter_functions
Project-URL: Documentation, https://filter-functions.readthedocs.io/en/latest/
Project-URL: Homepage, https://www.quantuminfo.physik.rwth-aachen.de/cms/Quantuminfo/Forschung/Quantum-Technology-Group/~zcsx/code/lidx/1/
Author: Quantum Technology Group, RWTH Aachen University
Author-email: Tobias Hangleiter <tobias.hangleiter@rwth-aachen.de>
License:                     GNU GENERAL PUBLIC LICENSE
License-File: LICENSE
Keywords: noise,numerics,physics,quantum computing,quantum information
Classifier: License :: OSI Approved :: GNU General Public License v3 or later (GPLv3+)
Classifier: Operating System :: OS Independent
Classifier: Programming Language :: Python :: 3 :: Only
Classifier: Programming Language :: Python :: 3.9
Classifier: Programming Language :: Python :: 3.10
Classifier: Programming Language :: Python :: 3.11
Classifier: Programming Language :: Python :: 3.12
Classifier: Programming Language :: Python :: 3.13
Classifier: Topic :: Scientific/Engineering :: Physics
Requires-Dist: numpy
Requires-Dist: opt-einsum
Requires-Dist: scipy
Requires-Dist: sparse
Requires-Dist: tqdm
Provides-Extra: all
Requires-Dist: codecov; extra == 'all'
Requires-Dist: ipympl; extra == 'all'
Requires-Dist: jupyter; extra == 'all'
Requires-Dist: matplotlib; extra == 'all'
Requires-Dist: nbsphinx; extra == 'all'
Requires-Dist: numpy; extra == 'all'
Requires-Dist: numpydoc; extra == 'all'
Requires-Dist: pytest-cov; extra == 'all'
Requires-Dist: pytest>=4.6; extra == 'all'
Requires-Dist: qutip; extra == 'all'
Requires-Dist: qutip-qip; extra == 'all'
Requires-Dist: qutip-qtrl>=0.1.4; extra == 'all'
Requires-Dist: sphinx; extra == 'all'
Requires-Dist: sphinx-rtd-theme; extra == 'all'
Requires-Dist: sphinxcontrib-apidoc; extra == 'all'
Provides-Extra: bloch-sphere-visualization
Requires-Dist: matplotlib; extra == 'bloch-sphere-visualization'
Requires-Dist: qutip; extra == 'bloch-sphere-visualization'
Provides-Extra: doc
Requires-Dist: ipympl; extra == 'doc'
Requires-Dist: jupyter; extra == 'doc'
Requires-Dist: nbsphinx; extra == 'doc'
Requires-Dist: numpy; extra == 'doc'
Requires-Dist: numpydoc; extra == 'doc'
Requires-Dist: qutip-qip; extra == 'doc'
Requires-Dist: qutip-qtrl>=0.1.4; extra == 'doc'
Requires-Dist: sphinx; extra == 'doc'
Requires-Dist: sphinx-rtd-theme; extra == 'doc'
Requires-Dist: sphinxcontrib-apidoc; extra == 'doc'
Provides-Extra: plotting
Requires-Dist: matplotlib; extra == 'plotting'
Provides-Extra: tests
Requires-Dist: codecov; extra == 'tests'
Requires-Dist: pytest-cov; extra == 'tests'
Requires-Dist: pytest>=4.6; extra == 'tests'
